ml_quant_risk/MC.py
ml_quant_risk/VaR.py
ml_quant_risk/__init__.py
ml_quant_risk/regression.py
ml_quant_risk-0.3.2.dist-info/METADATA
ml_quant_risk-0.3.2.dist-info/WHEEL
ml_quant_risk-0.3.2.dist-info/top_level.txt
ml_quant_risk-0.3.2.dist-info/RECORD
