Metadata-Version: 2.1
Name: ml-quant-risk
Version: 0.3.2
Summary: Quatitative risk management
Home-page: UNKNOWN
Author: Muge Li
License: UNKNOWN
Platform: UNKNOWN
Requires-Python: >=3.6
